czipdecrypter.cpython-39-x86_64-linux-gnu.so
cxzip-1.0.0.dist-info/top_level.txt
cxzip-1.0.0.dist-info/METADATA
cxzip-1.0.0.dist-info/WHEEL
cxzip-1.0.0.dist-info/RECORD
cxzip-1.0.0.dist-info/LICENSE
cxzip-1.0.0.data/data/czipdecrypter.c
cxzip-1.0.0.data/data/czipdecrypter.pyx
cxzip-1.0.0.data/data/crctable.c
cxzip-1.0.0.data/data/cfunc.c
