Metadata-Version: 2.1
Name: cxzip
Version: 1.0.0
Summary: Drip-in replacement of zipfile._ZipDecrypter for python 3.7+
Home-page: https://github.com/multiSnow/czipdecrypter
Author: Cognexa Solutions s.r.o.
Author-email: info@cognexa.com
License: UNKNOWN
Keywords: zipfile,zip,decryption
Platform: UNKNOWN
Classifier: Development Status :: 3 - Alpha
Classifier: License :: OSI Approved :: ISC License (ISCL)
Classifier: Programming Language :: C
Classifier: Programming Language :: Cython
License-File: LICENSE
